{
  "last_updated": "2025-06-10T02:17:45.654794-04:00",
  "stories": [
    {
      "title": "Tell HN: Help restore the tax deduction for software dev in the US (Section 174)",
      "score": 1785,
      "url": "https://news.ycombinator.com/item?id=44226145",
      "time": 1749486531.0,
      "comments_url": "https://news.ycombinator.com/item?id=44226145"
    },
    {
      "title": "Containerization is a Swift package for running Linux containers on macOS",
      "score": 431,
      "url": "https://github.com/apple/containerization",
      "time": 1749502409.0,
      "comments_url": "https://news.ycombinator.com/item?id=44229348"
    },
    {
      "title": "Apple announces Foundation Models and Containerization frameworks, etc",
      "score": 611,
      "url": "https://www.apple.com/newsroom/2025/06/apple-supercharges-its-tools-and-technologies-for-developers/",
      "time": 1749491056.0,
      "comments_url": "https://news.ycombinator.com/item?id=44226978"
    },
    {
      "title": "Discrete Mathematics: An Open Introduction [pdf]",
      "score": 73,
      "url": "https://discrete.openmathbooks.org/pdfs/dmoi4.pdf",
      "time": 1749520087.0,
      "comments_url": "https://news.ycombinator.com/item?id=44231649"
    },
    {
      "title": "Micrographia (1665) [pdf]",
      "score": 15,
      "url": "https://arhipa.org/libros/Hooke_Robert_Micrographia-1665.pdf",
      "time": 1749531472.0,
      "comments_url": "https://news.ycombinator.com/item?id=44232699"
    },
    {
      "title": "Apple has announced its final version of macOS for Intel",
      "score": 19,
      "url": "https://tedium.co/2025/06/09/apple-wwdc-intel-mac-support-ending/",
      "time": 1749527516.0,
      "comments_url": "https://news.ycombinator.com/item?id=44232296"
    },
    {
      "title": "Implementing DOES> in Forth, the entire reason I started this mess",
      "score": 64,
      "url": "https://boston.conman.org/2025/06/09.1",
      "time": 1749519399.0,
      "comments_url": "https://news.ycombinator.com/item?id=44231594"
    },
    {
      "title": "Sly Stone has died",
      "score": 234,
      "url": "https://abcnews.go.com/US/sly-stone-pioneering-leader-funk-band-sly-family/story?id=122666345",
      "time": 1749505345.0,
      "comments_url": "https://news.ycombinator.com/item?id=44229841"
    },
    {
      "title": "Scientific Papers: Innovation or Imitation?",
      "score": 15,
      "url": "https://www.johndcook.com/blog/2025/06/05/scientific-papers-innovation-or-imitation/",
      "time": 1749528281.0,
      "comments_url": "https://news.ycombinator.com/item?id=44232371"
    },
    {
      "title": "Working with the EPA to Secure Exposed Water HMIs",
      "score": 23,
      "url": "https://censys.com/blog/turning-off-the-information-flow-working-with-the-epa-to-secure-hundreds-of-exposed-water-hmis",
      "time": 1749279221.0,
      "comments_url": "https://news.ycombinator.com/item?id=44207943"
    },
    {
      "title": "Container: Apple's Linux-Container Runtime",
      "score": 145,
      "url": "https://github.com/apple/container",
      "time": 1749501743.0,
      "comments_url": "https://news.ycombinator.com/item?id=44229239"
    },
    {
      "title": "Why agents are bad pair programmers",
      "score": 95,
      "url": "https://justin.searls.co/posts/why-agents-are-bad-pair-programmers/",
      "time": 1749512183.0,
      "comments_url": "https://news.ycombinator.com/item?id=44230838"
    },
    {
      "title": "Show HN: Munal OS: a graphical experimental OS with WASM sandboxing",
      "score": 216,
      "url": "https://github.com/Askannz/munal-os",
      "time": 1749490469.0,
      "comments_url": "https://news.ycombinator.com/item?id=44226879"
    },
    {
      "title": "The Xerox Alto, Smalltalk, and rewriting a running GUI (2017)",
      "score": 71,
      "url": "https://www.righto.com/2017/10/the-xerox-alto-smalltalk-and-rewriting.html",
      "time": 1749504344.0,
      "comments_url": "https://news.ycombinator.com/item?id=44229694"
    },
    {
      "title": "Apple introduces a universal design across platforms",
      "score": 521,
      "url": "https://www.apple.com/newsroom/2025/06/apple-introduces-a-delightful-and-elegant-new-software-design/",
      "time": 1749488987.0,
      "comments_url": "https://news.ycombinator.com/item?id=44226612"
    },
    {
      "title": "Launch HN: Chonkie (YC X25) – Open-Source Library for Advanced Chunking",
      "score": 118,
      "url": "https://news.ycombinator.com/item?id=44225930",
      "time": 1749485343.0,
      "comments_url": "https://news.ycombinator.com/item?id=44225930"
    },
    {
      "title": "Go is a good fit for agents",
      "score": 148,
      "url": "https://docs.hatchet.run/blog/go-agents",
      "time": 1749039279.0,
      "comments_url": "https://news.ycombinator.com/item?id=44179889"
    },
    {
      "title": "Las Vegas is embracing a simple climate solution: More trees",
      "score": 115,
      "url": "https://www.npr.org/2025/06/09/nx-s1-5340363/las-vegas-climate-change-solution-trees",
      "time": 1749514900.0,
      "comments_url": "https://news.ycombinator.com/item?id=44231151"
    },
    {
      "title": "Marines being mobilized in response to LA protests",
      "score": 256,
      "url": "https://www.cnn.com/2025/06/09/politics/marines-mobilized-los-angeles-protests",
      "time": 1749507669.0,
      "comments_url": "https://news.ycombinator.com/item?id=44230182"
    },
    {
      "title": "Doctors could hack the nervous system with ultrasound",
      "score": 134,
      "url": "https://spectrum.ieee.org/focused-ultrasound-stimulation-inflammation-diabetes",
      "time": 1749479250.0,
      "comments_url": "https://news.ycombinator.com/item?id=44224874"
    }
  ]
}