{
  "last_updated": "2026-05-21T15:43:23.716977-04:00",
  "stories": [
    {
      "title": "Amazon, Facebook, FBI have access to a private intelligence-sharing network",
      "score": 274,
      "url": "https://prismreports.org/2026/05/20/seattle-shield-private-companies-surveillance/",
      "time": 1779386158.0,
      "comments_url": "https://news.ycombinator.com/item?id=48226588"
    },
    {
      "title": "BBEdit 16",
      "score": 108,
      "url": "https://www.barebones.com/products/bbedit/bbedit16.html",
      "time": 1779387697.0,
      "comments_url": "https://news.ycombinator.com/item?id=48226944"
    },
    {
      "title": "Project Hail Mary – Stellar Navigation Chart",
      "score": 220,
      "url": "https://valhovey.github.io/gaia-mary/",
      "time": 1779380591.0,
      "comments_url": "https://news.ycombinator.com/item?id=48225297"
    },
    {
      "title": "More than 340 local news outlets are limiting the Internet Archive's access",
      "score": 102,
      "url": "https://www.niemanlab.org/2026/05/more-than-340-local-news-outlets-are-limiting-the-internet-archives-access-to-their-journalism/",
      "time": 1779382767.0,
      "comments_url": "https://news.ycombinator.com/item?id=48225838"
    },
    {
      "title": "Flipper One – we need your help",
      "score": 870,
      "url": "https://blog.flipper.net/flipper-one-we-need-your-help/",
      "time": 1779361418.0,
      "comments_url": "https://news.ycombinator.com/item?id=48220647"
    },
    {
      "title": "Indexing a year of video locally on a 2021 MacBook with Gemma4-31B (50GB swap)",
      "score": 189,
      "url": "https://blog.simbastack.com/indexed-a-year-of-video-locally/",
      "time": 1779372097.0,
      "comments_url": "https://news.ycombinator.com/item?id=48222733"
    },
    {
      "title": "Where are all the UK red telephone kiosks?",
      "score": 28,
      "url": "https://www.thek6project.co.uk/",
      "time": 1779386657.0,
      "comments_url": "https://news.ycombinator.com/item?id=48226703"
    },
    {
      "title": "Python 3.15: features that didn't make the headlines",
      "score": 261,
      "url": "https://blog.changs.co.uk/python-315-features-that-didnt-make-the-headlines.html",
      "time": 1779361811.0,
      "comments_url": "https://news.ycombinator.com/item?id=48220696"
    },
    {
      "title": "Lost Images from the 1945 Trinity Nuclear Test Restored",
      "score": 224,
      "url": "https://spectrum.ieee.org/trinity-nuclear-test",
      "time": 1779361346.0,
      "comments_url": "https://news.ycombinator.com/item?id=48220639"
    },
    {
      "title": "Launch HN: Runtime (YC P26) – Sandboxed coding agents for everyone on a team",
      "score": 38,
      "url": "https://www.runtm.com/",
      "time": 1779379633.0,
      "comments_url": "https://news.ycombinator.com/item?id=48225040"
    },
    {
      "title": "ParadeDB (YC S23) Is Hiring Distributed Systems/Platform Engineers",
      "score": 1,
      "url": "https://news.ycombinator.com/item?id=48225852",
      "time": 1779382852.0,
      "comments_url": "https://news.ycombinator.com/item?id=48225852"
    },
    {
      "title": "Bournegol???",
      "score": 17,
      "url": "https://oldhome.schmorp.de/marc/bournegol.html",
      "time": 1779183178.0,
      "comments_url": "https://news.ycombinator.com/item?id=48191192"
    },
    {
      "title": "Mounting Git commits as folders with NFS",
      "score": 65,
      "url": "https://jvns.ca/blog/2023/12/04/mounting-git-commits-as-folders-with-nfs/",
      "time": 1779175976.0,
      "comments_url": "https://news.ycombinator.com/item?id=48190373"
    },
    {
      "title": "We're testing new ad formats in Search and expanding our Direct Offers pilot",
      "score": 503,
      "url": "https://blog.google/products/ads-commerce/google-marketing-live-search-ads/",
      "time": 1779356986.0,
      "comments_url": "https://news.ycombinator.com/item?id=48220105"
    },
    {
      "title": "Show HN: Agent.email – sign up via curl, claim with a human OTP",
      "score": 19,
      "url": "https://news.ycombinator.com/item?id=48225596",
      "time": 1779381754.0,
      "comments_url": "https://news.ycombinator.com/item?id=48225596"
    },
    {
      "title": "Show HN: Freenet, a peer-to-peer platform for decentralized apps",
      "score": 14,
      "url": "https://freenet.org/",
      "time": 1779374097.0,
      "comments_url": "https://news.ycombinator.com/item?id=48223362"
    },
    {
      "title": "When Rails-way does not work anymore?",
      "score": 6,
      "url": "https://paweldabrowski.com/farewell-to-rails-way/when-rails-way-does-not-work",
      "time": 1779197322.0,
      "comments_url": "https://news.ycombinator.com/item?id=48193089"
    },
    {
      "title": "Museum of Pocket Calculating Devices",
      "score": 38,
      "url": "https://www.calculators.de/",
      "time": 1779378604.0,
      "comments_url": "https://news.ycombinator.com/item?id=48224768"
    },
    {
      "title": "What Is Happening to Publishing?",
      "score": 50,
      "url": "https://resobscura.substack.com/p/what-is-happening-to-publishing",
      "time": 1779222224.0,
      "comments_url": "https://news.ycombinator.com/item?id=48199011"
    },
    {
      "title": "Show HN: I Dedicated 4 Years to Mastering Offline Password Cracking",
      "score": 175,
      "url": "https://news.ycombinator.com/item?id=48221896",
      "time": 1779368197.0,
      "comments_url": "https://news.ycombinator.com/item?id=48221896"
    }
  ]
}