{
  "last_updated": "2025-06-11T14:16:57.512786-04:00",
  "stories": [
    {
      "title": "Dolly Parton's Dollywood Express",
      "score": 54,
      "url": "https://thetransitguy.substack.com/p/dolly-parton-runs-a-train-busier",
      "time": 1749660408.0,
      "comments_url": "https://news.ycombinator.com/item?id=44249417"
    },
    {
      "title": "V-JEPA 2 world model and new benchmarks for physical reasoning",
      "score": 126,
      "url": "https://ai.meta.com/blog/v-jepa-2-world-model-benchmarks/",
      "time": 1749653007.0,
      "comments_url": "https://news.ycombinator.com/item?id=44248165"
    },
    {
      "title": "The Beach Boys' Brian Wilson Dies at 82",
      "score": 200,
      "url": "https://pitchfork.com/news/the-beach-boys-brian-wilson-dies-at-82/",
      "time": 1749660769.0,
      "comments_url": "https://news.ycombinator.com/item?id=44249467"
    },
    {
      "title": "Show HN: RomM – An open-source, self-hosted ROM manager and player",
      "score": 103,
      "url": "https://github.com/rommapp/romm",
      "time": 1749651905.0,
      "comments_url": "https://news.ycombinator.com/item?id=44247964"
    },
    {
      "title": "Show HN: Spark, An advanced 3D Gaussian Splatting renderer for Three.js",
      "score": 48,
      "url": "https://sparkjs.dev/",
      "time": 1749661376.0,
      "comments_url": "https://news.ycombinator.com/item?id=44249565"
    },
    {
      "title": "Show HN: Ikuyo a Travel Planning Web Application",
      "score": 161,
      "url": "https://ikuyo.kenrick95.org/",
      "time": 1749645855.0,
      "comments_url": "https://news.ycombinator.com/item?id=44247029"
    },
    {
      "title": "Plants hear their pollinators, and produce sweet nectar in response",
      "score": 102,
      "url": "https://www.cbc.ca/listen/live-radio/1-51-quirks-and-quarks/clip/16150976-plants-hear-pollinators-produce-sweet-nectar-response",
      "time": 1749324458.0,
      "comments_url": "https://news.ycombinator.com/item?id=44211971"
    },
    {
      "title": "How I Program with Agents",
      "score": 226,
      "url": "https://crawshaw.io/blog/programming-with-agents",
      "time": 1749447014.0,
      "comments_url": "https://news.ycombinator.com/item?id=44221655"
    },
    {
      "title": "Show HN: S3mini – Tiny and fast S3-compatible client, no-deps, edge-ready",
      "score": 169,
      "url": "https://github.com/good-lly/s3mini",
      "time": 1749632147.0,
      "comments_url": "https://news.ycombinator.com/item?id=44245577"
    },
    {
      "title": "The Diary of Samuel Pepys",
      "score": 26,
      "url": "https://www.historytoday.com/archive/feature/hidden-diary-samuel-pepys",
      "time": 1749357699.0,
      "comments_url": "https://news.ycombinator.com/item?id=44214588"
    },
    {
      "title": "OpenPlanetData – Free Daily Planet OSM PBF and GOL Indexed Snapshots",
      "score": 47,
      "url": "https://openplanetdata.com",
      "time": 1749646543.0,
      "comments_url": "https://news.ycombinator.com/item?id=44247119"
    },
    {
      "title": "Medical Aid in Dying, My Health, and So On",
      "score": 61,
      "url": "https://blog.the-brannons.com/post/Medical-Aid-in-Dying-My-Health-and-so-on",
      "time": 1749659615.0,
      "comments_url": "https://news.ycombinator.com/item?id=44249303"
    },
    {
      "title": "Launch HN: Vassar Robotics (YC X25) – $219 robot arm that learns new skills",
      "score": 521,
      "url": "https://news.ycombinator.com/item?id=44240302",
      "time": 1749582737.0,
      "comments_url": "https://news.ycombinator.com/item?id=44240302"
    },
    {
      "title": "DeskHog, an open-source developer toy",
      "score": 31,
      "url": "https://posthog.com/deskhog",
      "time": 1749649051.0,
      "comments_url": "https://news.ycombinator.com/item?id=44247501"
    },
    {
      "title": "Publish a Python Wheel to GCP Artifact Registry with Poetry",
      "score": 13,
      "url": "https://sergiolema.dev/2025/06/09/publish-a-python-wheel-to-gcp-artifact-registry-with-poetry/",
      "time": 1749452783.0,
      "comments_url": "https://news.ycombinator.com/item?id=44222074"
    },
    {
      "title": "Mapbox Geospatial MCP Server",
      "score": 76,
      "url": "https://github.com/mapbox/mcp-server",
      "time": 1749646586.0,
      "comments_url": "https://news.ycombinator.com/item?id=44247124"
    },
    {
      "title": "Bypassing GitHub Actions policies in the dumbest way possible",
      "score": 88,
      "url": "https://blog.yossarian.net/2025/06/11/github-actions-policies-dumb-bypass",
      "time": 1749651354.0,
      "comments_url": "https://news.ycombinator.com/item?id=44247881"
    },
    {
      "title": "Lessons from That 1834 Landscape Gardening Guidebook",
      "score": 87,
      "url": "https://fi-le.net/pueckler/",
      "time": 1749332895.0,
      "comments_url": "https://news.ycombinator.com/item?id=44212911"
    },
    {
      "title": "Magistral — the first reasoning model by Mistral AI",
      "score": 867,
      "url": "https://mistral.ai/news/magistral",
      "time": 1749564481.0,
      "comments_url": "https://news.ycombinator.com/item?id=44236997"
    },
    {
      "title": "Markdown Ninja: markdown-first CMS for bloggers, minimalists and startups.",
      "score": 18,
      "url": "https://github.com/bloom42/markdown-ninja",
      "time": 1749660412.0,
      "comments_url": "https://news.ycombinator.com/item?id=44249418"
    }
  ]
}