{
  "last_updated": "2025-09-20T02:15:31.872169-04:00",
  "stories": [
    {
      "title": "Less is safer: How Obsidian reduces the risk of supply chain attacks",
      "score": 247,
      "url": "https://obsidian.md/blog/less-is-safer/",
      "time": 1758319349.0,
      "comments_url": "https://news.ycombinator.com/item?id=45307242"
    },
    {
      "title": "If all the world were a monorepo",
      "score": 85,
      "url": "https://jtibs.substack.com/p/if-all-the-world-were-a-monorepo",
      "time": 1758011625.0,
      "comments_url": "https://news.ycombinator.com/item?id=45259623"
    },
    {
      "title": "Hidden risk in Notion 3.0 AI agents: Web search tool abuse for data exfiltration",
      "score": 99,
      "url": "https://www.codeintegrity.ai/blog/notion",
      "time": 1758318577.0,
      "comments_url": "https://news.ycombinator.com/item?id=45307095"
    },
    {
      "title": "Feedmaker: URL + CSS selectors = RSS feed",
      "score": 105,
      "url": "https://feedmaker.fly.dev",
      "time": 1758316496.0,
      "comments_url": "https://news.ycombinator.com/item?id=45306701"
    },
    {
      "title": "High-performance read-through cache for object storage",
      "score": 9,
      "url": "https://github.com/s2-streamstore/cachey",
      "time": 1758341597.0,
      "comments_url": "https://news.ycombinator.com/item?id=45310294"
    },
    {
      "title": "Ants that seem to defy biology – They lay eggs that hatch into another species",
      "score": 360,
      "url": "https://www.smithsonianmag.com/smart-news/these-ant-queens-seem-to-defy-biology-they-lay-eggs-that-hatch-into-another-species-180987292/",
      "time": 1758284750.0,
      "comments_url": "https://news.ycombinator.com/item?id=45300865"
    },
    {
      "title": "Show HN: WeUseElixir - Elixir project directory",
      "score": 121,
      "url": "https://weuseelixir.com/",
      "time": 1758313514.0,
      "comments_url": "https://news.ycombinator.com/item?id=45306120"
    },
    {
      "title": "A 3D-Printed Business Card Embosser",
      "score": 53,
      "url": "https://www.core77.com/posts/138492/A-3D-Printed-Business-Card-Embosser",
      "time": 1758126254.0,
      "comments_url": "https://news.ycombinator.com/item?id=45277900"
    },
    {
      "title": "Internet Archive's big battle with music publishers ends in settlement",
      "score": 295,
      "url": "https://arstechnica.com/tech-policy/2025/09/internet-archives-big-battle-with-music-publishers-ends-in-settlement/",
      "time": 1757975655.0,
      "comments_url": "https://news.ycombinator.com/item?id=45255785"
    },
    {
      "title": "The best YouTube downloaders, and how Google silenced the press",
      "score": 258,
      "url": "https://windowsread.me/p/best-youtube-downloaders",
      "time": 1758284410.0,
      "comments_url": "https://news.ycombinator.com/item?id=45300810"
    },
    {
      "title": "Ruby Central's Attack on RubyGems [pdf]",
      "score": 627,
      "url": "https://pup-e.com/goodbye-rubygems.pdf",
      "time": 1758269357.0,
      "comments_url": "https://news.ycombinator.com/item?id=45299170"
    },
    {
      "title": "Three-Minute Take-Home Test May Identify Symptoms Linked to Alzheimer's Disease",
      "score": 77,
      "url": "https://www.smithsonianmag.com/smart-news/three-minute-take-home-test-may-identify-symptoms-linked-to-alzheimers-disease-years-before-a-traditional-diagnosis-180987281/",
      "time": 1758308582.0,
      "comments_url": "https://news.ycombinator.com/item?id=45305180"
    },
    {
      "title": "Faster Argmin on Floats",
      "score": 10,
      "url": "https://algorithmiker.github.io/faster-float-argmin/",
      "time": 1758212446.0,
      "comments_url": "https://news.ycombinator.com/item?id=45291538"
    },
    {
      "title": "Supporting Our AI Overlords: Redesigning Data Systems to Be Agent-First",
      "score": 5,
      "url": "https://arxiv.org/abs/2509.00997",
      "time": 1758339683.0,
      "comments_url": "https://news.ycombinator.com/item?id=45310123"
    },
    {
      "title": "Kernel: Introduce Multikernel Architecture Support",
      "score": 135,
      "url": "https://lwn.net/ml/all/20250918222607.186488-1-xiyou.wangcong@gmail.com/",
      "time": 1758295765.0,
      "comments_url": "https://news.ycombinator.com/item?id=45302721"
    },
    {
      "title": "Your very own humane interface: Try Jef Raskin's ideas at home",
      "score": 81,
      "url": "https://arstechnica.com/gadgets/2025/09/your-very-own-humane-interface-try-jef-raskins-ideas-at-home/",
      "time": 1758303813.0,
      "comments_url": "https://news.ycombinator.com/item?id=45304379"
    },
    {
      "title": "Starfront Observatories",
      "score": 35,
      "url": "https://starfront.space/",
      "time": 1758077953.0,
      "comments_url": "https://news.ycombinator.com/item?id=45271108"
    },
    {
      "title": "Show HN: Zedis – A Redis clone I'm writing in Zig",
      "score": 78,
      "url": "https://github.com/barddoo/zedis",
      "time": 1758318943.0,
      "comments_url": "https://news.ycombinator.com/item?id=45307166"
    },
    {
      "title": "Shipping 100 hardware units in under eight weeks",
      "score": 122,
      "url": "https://farhanhossain.substack.com/p/how-we-shipped-100-hardware-units",
      "time": 1758226289.0,
      "comments_url": "https://news.ycombinator.com/item?id=45294390"
    },
    {
      "title": "An untidy history of AI across four books",
      "score": 98,
      "url": "https://hedgehogreview.com/issues/lessons-of-babel/articles/perplexity",
      "time": 1758305718.0,
      "comments_url": "https://news.ycombinator.com/item?id=45304706"
    }
  ]
}