{
  "last_updated": "2026-05-08T15:04:37.682591-04:00",
  "stories": [
    {
      "title": "Google Cloud Fraud Defence is just WEI repackaged",
      "score": 429,
      "url": "https://privatecaptcha.com/blog/google-cloud-fraud-defence-wei/",
      "time": 1778248570.0,
      "comments_url": "https://news.ycombinator.com/item?id=48063199"
    },
    {
      "title": "Cartoon Network Flash Games",
      "score": 141,
      "url": "https://www.webdesignmuseum.org/flash-game-exhibitions/cartoon-network-flash-games",
      "time": 1778257792.0,
      "comments_url": "https://news.ycombinator.com/item?id=48065360"
    },
    {
      "title": "AI Is Breaking Two Vulnerability Cultures",
      "score": 33,
      "url": "https://www.jefftk.com/p/ai-is-breaking-two-vulnerability-cultures",
      "time": 1778262908.0,
      "comments_url": "https://news.ycombinator.com/item?id=48066524"
    },
    {
      "title": "Serving a website on a Raspberry Pi Zero running in RAM",
      "score": 132,
      "url": "https://btxx.org/posts/memory/",
      "time": 1778253035.0,
      "comments_url": "https://news.ycombinator.com/item?id=48064312"
    },
    {
      "title": "An Introduction to Meshtastic",
      "score": 284,
      "url": "https://meshtastic.org/docs/introduction/",
      "time": 1778239331.0,
      "comments_url": "https://news.ycombinator.com/item?id=48061566"
    },
    {
      "title": "A web page that shows you everything the browser told it without asking",
      "score": 341,
      "url": "https://sinceyouarrived.world/taken",
      "time": 1778243825.0,
      "comments_url": "https://news.ycombinator.com/item?id=48062178"
    },
    {
      "title": "PC Engine CPU",
      "score": 88,
      "url": "https://jsgroth.dev/blog/posts/pc-engine-cpu/",
      "time": 1778249671.0,
      "comments_url": "https://news.ycombinator.com/item?id=48063521"
    },
    {
      "title": "Bjarne Stroustrup: How do I deal with memory leaks? (2022)",
      "score": 34,
      "url": "https://www.stroustrup.com/bs_faq2.html#memory-leaks",
      "time": 1778260019.0,
      "comments_url": "https://news.ycombinator.com/item?id=48065916"
    },
    {
      "title": "Apple, Intel have reached preliminary chip-making deal",
      "score": 86,
      "url": "https://www.reuters.com/business/apple-intel-have-reached-preliminary-chip-making-deal-wsj-reports-2026-05-08/",
      "time": 1778261121.0,
      "comments_url": "https://news.ycombinator.com/item?id=48066169"
    },
    {
      "title": "Poland is now among the 20 largest economies",
      "score": 744,
      "url": "https://apnews.com/article/poland-economy-growth-g20-gdp-26fe06e120398410f8d773ba5661e7aa",
      "time": 1778243405.0,
      "comments_url": "https://news.ycombinator.com/item?id=48062117"
    },
    {
      "title": "Rumors of my death are slightly exaggerated",
      "score": 1139,
      "url": "https://news.ycombinator.com/item?id=48037336",
      "time": 1778081091.0,
      "comments_url": "https://news.ycombinator.com/item?id=48037336"
    },
    {
      "title": "Mojo 1.0 Beta",
      "score": 176,
      "url": "https://mojolang.org/",
      "time": 1778208541.0,
      "comments_url": "https://news.ycombinator.com/item?id=48057901"
    },
    {
      "title": "Cloudflare to cut about 20% of its workforce",
      "score": 1196,
      "url": "https://www.reuters.com/business/world-at-work/cloudflare-cut-over-1100-jobs-2026-05-07/",
      "time": 1778185417.0,
      "comments_url": "https://news.ycombinator.com/item?id=48054423"
    },
    {
      "title": "Show HN: Git for AI Agents",
      "score": 64,
      "url": "https://github.com/regent-vcs/re_gent",
      "time": 1778249736.0,
      "comments_url": "https://news.ycombinator.com/item?id=48063548"
    },
    {
      "title": "David Attenborough's 100th Birthday",
      "score": 115,
      "url": "https://www.bbc.com/news/articles/cp3pww9g0p5o",
      "time": 1778241806.0,
      "comments_url": "https://news.ycombinator.com/item?id=48061884"
    },
    {
      "title": "Canvas online again as ShinyHunters threatens to leak schools’ data",
      "score": 876,
      "url": "https://www.theverge.com/tech/926458/canvas-shinyhunters-breach",
      "time": 1778192541.0,
      "comments_url": "https://news.ycombinator.com/item?id=48055913"
    },
    {
      "title": "US Government releases first batch of UAP documents and videos",
      "score": 139,
      "url": "https://www.war.gov/UFO/",
      "time": 1778242225.0,
      "comments_url": "https://news.ycombinator.com/item?id=48061938"
    },
    {
      "title": "Podman rootless containers and the Copy Fail exploit",
      "score": 84,
      "url": "https://garrido.io/notes/podman-rootless-containers-copy-fail/",
      "time": 1778246553.0,
      "comments_url": "https://news.ycombinator.com/item?id=48062745"
    },
    {
      "title": "Maybe you shouldn't install new software for a bit",
      "score": 771,
      "url": "https://xeiaso.net/blog/2026/abstain-from-install/",
      "time": 1778194931.0,
      "comments_url": "https://news.ycombinator.com/item?id=48056227"
    },
    {
      "title": "GeoJSON",
      "score": 123,
      "url": "https://geojson.org/",
      "time": 1778234137.0,
      "comments_url": "https://news.ycombinator.com/item?id=48060918"
    }
  ]
}