{
  "last_updated": "2025-09-01T02:19:47.164802-04:00",
  "stories": [
    {
      "title": "We should have the ability to run any code we want on hardware we own",
      "score": 664,
      "url": "https://hugotunius.se/2025/08/31/what-every-argument-about-sideloading-gets-wrong.html",
      "time": 1756676786.0,
      "comments_url": "https://news.ycombinator.com/item?id=45087396"
    },
    {
      "title": "Eternal Struggle",
      "score": 420,
      "url": "https://yoavg.github.io/eternal/",
      "time": 1756667043.0,
      "comments_url": "https://news.ycombinator.com/item?id=45086020"
    },
    {
      "title": "Nintendo Switch 2 Dock USB-C Compatibility",
      "score": 136,
      "url": "https://www.lttlabs.com/blog/2025/08/30/nintendo-switch-2-dock",
      "time": 1756682506.0,
      "comments_url": "https://news.ycombinator.com/item?id=45087971"
    },
    {
      "title": "“This telegram must be closely paraphrased before being communicated to anyone”",
      "score": 588,
      "url": "https://history.stackexchange.com/questions/79371/this-telegram-must-be-closely-paraphrased-before-being-communicated-to-anyone",
      "time": 1756643987.0,
      "comments_url": "https://news.ycombinator.com/item?id=45082731"
    },
    {
      "title": "What brain surgery taught me about the fragile gift of consciousness",
      "score": 109,
      "url": "https://bigthink.com/business/brain-surgery-fragile-gift-of-consciousness/",
      "time": 1756390927.0,
      "comments_url": "https://news.ycombinator.com/item?id=45052517"
    },
    {
      "title": "Lewis and Clark marked their trail with laxatives",
      "score": 111,
      "url": "https://offbeatoregon.com/2501d1006d_biliousPills-686.077.html",
      "time": 1756680866.0,
      "comments_url": "https://news.ycombinator.com/item?id=45087815"
    },
    {
      "title": "Jujutsu for everyone",
      "score": 343,
      "url": "https://jj-for-everyone.github.io/",
      "time": 1756654264.0,
      "comments_url": "https://news.ycombinator.com/item?id=45083952"
    },
    {
      "title": "What Is Complexity in Chess?",
      "score": 12,
      "url": "https://lichess.org/@/Toadofsky/blog/what-is-complexity/pKo1swFh",
      "time": 1756698333.0,
      "comments_url": "https://news.ycombinator.com/item?id=45089256"
    },
    {
      "title": "Show HN: Spotilyrics – See synchronized Spotify lyrics inside VS Code",
      "score": 12,
      "url": "https://github.com/therepanic/spotilyrics",
      "time": 1756681759.0,
      "comments_url": "https://news.ycombinator.com/item?id=45087905"
    },
    {
      "title": "A Linux version of the Procmon Sysinternals tool",
      "score": 74,
      "url": "https://github.com/microsoft/ProcMon-for-Linux",
      "time": 1756680185.0,
      "comments_url": "https://news.ycombinator.com/item?id=45087748"
    },
    {
      "title": "A Crack in the Cosmos",
      "score": 38,
      "url": "https://drb.ie/articles/a-crack-in-the-cosmos/",
      "time": 1756613465.0,
      "comments_url": "https://news.ycombinator.com/item?id=45080313"
    },
    {
      "title": "What to do with C++ modules?",
      "score": 120,
      "url": "https://nibblestew.blogspot.com/2025/08/we-need-to-seriously-think-about-what.html",
      "time": 1756668121.0,
      "comments_url": "https://news.ycombinator.com/item?id=45086210"
    },
    {
      "title": "The Qweremin",
      "score": 32,
      "url": "https://www.linusakesson.net/qweremin/index.php",
      "time": 1756457121.0,
      "comments_url": "https://news.ycombinator.com/item?id=45061702"
    },
    {
      "title": "Ask HN: Best foundation model for CLM fine-tuning?",
      "score": 8,
      "url": "https://news.ycombinator.com/item?id=45050732",
      "time": 1756379320.0,
      "comments_url": "https://news.ycombinator.com/item?id=45050732"
    },
    {
      "title": "Hobbyist Maintainers with Thomas DePierre",
      "score": 11,
      "url": "https://opensourcesecurity.io/2025/2025-06-hobbyist-thomas-depierre/",
      "time": 1756387937.0,
      "comments_url": "https://news.ycombinator.com/item?id=45051950"
    },
    {
      "title": "Pong Clock",
      "score": 76,
      "url": "https://bigjobby.com/pong/?v=2.0/",
      "time": 1756398571.0,
      "comments_url": "https://news.ycombinator.com/item?id=45054119"
    },
    {
      "title": "When the sun will literally set on what's left of the British Empire",
      "score": 164,
      "url": "https://oikofuge.com/sun-sets-on-british-empire/",
      "time": 1756660519.0,
      "comments_url": "https://news.ycombinator.com/item?id=45084913"
    },
    {
      "title": "Launch HN: VibeFlow (YC S25) – Web app generator with visual, editable workflows",
      "score": 82,
      "url": "https://news.ycombinator.com/item?id=45084759",
      "time": 1756659619.0,
      "comments_url": "https://news.ycombinator.com/item?id=45084759"
    },
    {
      "title": "Use One Big Server (2022)",
      "score": 168,
      "url": "https://specbranch.com/posts/one-big-server/",
      "time": 1756661347.0,
      "comments_url": "https://news.ycombinator.com/item?id=45085029"
    },
    {
      "title": "Ford and the Birth of the Model T",
      "score": 22,
      "url": "https://www.construction-physics.com/p/ford-and-the-birth-of-the-model-t",
      "time": 1756425168.0,
      "comments_url": "https://news.ycombinator.com/item?id=45058349"
    }
  ]
}