{
  "last_updated": "2025-10-11T05:10:30.562726-04:00",
  "stories": [
    {
      "title": "HTML's Best Kept Secret: The Output Tag",
      "score": 69,
      "url": "https://denodell.com/blog/html-best-kept-secret-output-tag",
      "time": 1760171246.0,
      "comments_url": "https://news.ycombinator.com/item?id=45547566"
    },
    {
      "title": "AMD and Sony's PS6 chipset aims to rethink the current graphics pipeline",
      "score": 86,
      "url": "https://arstechnica.com/gaming/2025/10/amd-and-sony-tease-new-chip-architecture-ahead-of-playstation-6/",
      "time": 1760157376.0,
      "comments_url": "https://news.ycombinator.com/item?id=45546593"
    },
    {
      "title": "I built physical album cards with NFC tags to teach my son music discovery",
      "score": 362,
      "url": "https://fulghum.io/album-cards",
      "time": 1760128459.0,
      "comments_url": "https://news.ycombinator.com/item?id=45543475"
    },
    {
      "title": "(Re)Introducing the Pebble Appstore",
      "score": 158,
      "url": "https://ericmigi.com/blog/re-introducing-the-pebble-appstore/",
      "time": 1760133228.0,
      "comments_url": "https://news.ycombinator.com/item?id=45544228"
    },
    {
      "title": "How hard do you have to hit a chicken to cook it? (2020)",
      "score": 62,
      "url": "https://james-simon.github.io/blog/chicken-cooking/",
      "time": 1760148362.0,
      "comments_url": "https://news.ycombinator.com/item?id=45545965"
    },
    {
      "title": "Tangled, a Git collaboration platform built on atproto",
      "score": 183,
      "url": "https://blog.tangled.org/intro",
      "time": 1760131135.0,
      "comments_url": "https://news.ycombinator.com/item?id=45543899"
    },
    {
      "title": "AV2 video codec delivers 30% lower bitrate than AV1, final spec due in late 2025",
      "score": 17,
      "url": "https://videocardz.com/newz/av2-video-codec-delivers-30-lower-bitrate-than-av1-final-spec-due-in-late-2025",
      "time": 1760170771.0,
      "comments_url": "https://news.ycombinator.com/item?id=45547537"
    },
    {
      "title": "Does our “need for speed” make our wi-fi suck?",
      "score": 182,
      "url": "https://orb.net/blog/does-speed-make-wifi-suck",
      "time": 1760122530.0,
      "comments_url": "https://news.ycombinator.com/item?id=45542444"
    },
    {
      "title": "Synthetic aperture radar autofocus and calibration",
      "score": 84,
      "url": "https://hforsten.com/synthetic-aperture-radar-autofocus-and-calibration.html",
      "time": 1759900293.0,
      "comments_url": "https://news.ycombinator.com/item?id=45512300"
    },
    {
      "title": "Show HN: Semantic search over the National Gallery of Art",
      "score": 111,
      "url": "https://nga.demo.mixedbread.com/",
      "time": 1760128405.0,
      "comments_url": "https://news.ycombinator.com/item?id=45543471"
    },
    {
      "title": "Show HN: I invented a new generative model and got accepted to ICLR",
      "score": 561,
      "url": "https://discrete-distribution-networks.github.io/",
      "time": 1760086914.0,
      "comments_url": "https://news.ycombinator.com/item?id=45536694"
    },
    {
      "title": "Programming in the Sun: A Year with the Daylight Computer",
      "score": 73,
      "url": "https://wickstrom.tech/2025-10-10-programming-in-the-sun-a-year-with-the-daylight-computer.html",
      "time": 1760140273.0,
      "comments_url": "https://news.ycombinator.com/item?id=45545098"
    },
    {
      "title": "Intelligent Search in Rails with Typesense",
      "score": 5,
      "url": "https://avohq.io/blog/intelligent-search-in-rails-with-typesense",
      "time": 1759910309.0,
      "comments_url": "https://news.ycombinator.com/item?id=45513355"
    },
    {
      "title": "Show HN: A Digital Twin of my coffee roaster that runs in the browser",
      "score": 97,
      "url": "https://autoroaster.com/",
      "time": 1759768287.0,
      "comments_url": "https://news.ycombinator.com/item?id=45493128"
    },
    {
      "title": "Lánczos Interpolation Explained (2022)",
      "score": 120,
      "url": "https://mazzo.li/posts/lanczos.html",
      "time": 1759650569.0,
      "comments_url": "https://news.ycombinator.com/item?id=45479694"
    },
    {
      "title": "Ryanair flight landed at Manchester airport with six minutes of fuel left",
      "score": 621,
      "url": "https://www.theguardian.com/business/2025/oct/10/ryanair-flight-landed-at-manchester-airport-with-six-minutes-of-fuel-left-flight-log-suggests",
      "time": 1760109064.0,
      "comments_url": "https://news.ycombinator.com/item?id=45539943"
    },
    {
      "title": "OpenGL: Mesh shaders in the current year",
      "score": 144,
      "url": "https://www.supergoodcode.com/mesh-shaders-in-the-current-year/",
      "time": 1760097365.0,
      "comments_url": "https://news.ycombinator.com/item?id=45537890"
    },
    {
      "title": "HATEOAS for Haunted Houses",
      "score": 26,
      "url": "https://www.sanfordtech.xyz/posts/hateoas-for-haunted-houses/",
      "time": 1759925610.0,
      "comments_url": "https://news.ycombinator.com/item?id=45515290"
    },
    {
      "title": "Verge Genomics (YC S15) Is Hiring for Multiple Engineering and Product Roles",
      "score": 1,
      "url": "https://news.ycombinator.com/item?id=45544636",
      "time": 1760135836.0,
      "comments_url": "https://news.ycombinator.com/item?id=45544636"
    },
    {
      "title": "After nine years of grinding, Replit found its market. Can it keep it?",
      "score": 127,
      "url": "https://techcrunch.com/2025/10/02/after-nine-years-of-grinding-replit-finally-found-its-market-can-it-keep-it/",
      "time": 1759705346.0,
      "comments_url": "https://news.ycombinator.com/item?id=45486035"
    }
  ]
}