{
  "last_updated": "2026-04-04T17:23:02.349079-04:00",
  "stories": [
    {
      "title": "Electrons in moiré crystals explore higher-dimensional quantum worlds",
      "url": "https://news.mit.edu/2026/electrons-in-moire-crystals-explore-higher-dimensional-quantum-worlds-0403",
      "time": 1775251800.0,
      "published_at_eastern": "2026-04-03T17:30:00-04:00"
    },
    {
      "title": "Urban planning students engage with communities through the Freedom Summer Fellowship",
      "url": "https://news.mit.edu/2026/urban-planning-students-engage-communities-through-freedom-summer-fellowship-0403",
      "time": 1775250900.0,
      "published_at_eastern": "2026-04-03T17:15:00-04:00"
    },
    {
      "title": "Why does wealth inequality matter?",
      "url": "https://news.mit.edu/2026/why-does-wealth-inequality-matter-0403",
      "time": 1775250000.0,
      "published_at_eastern": "2026-04-03T17:00:00-04:00"
    },
    {
      "title": "Working to advance the nuclear renaissance",
      "url": "https://news.mit.edu/2026/working-to-advance-nuclear-renaissance-dean-price-0403",
      "time": 1775249700.0,
      "published_at_eastern": "2026-04-03T16:55:00-04:00"
    },
    {
      "title": "Toward cheaper, cleaner hydrogen production",
      "url": "https://news.mit.edu/2026/toward-cheaper-cleaner-hydrogen-production-0403",
      "time": 1775188800.0,
      "published_at_eastern": "2026-04-03T00:00:00-04:00"
    },
    {
      "title": "Lincoln Laboratory laser communications terminal launches on historic Artemis II moon mission",
      "url": "https://news.mit.edu/2026/lincoln-laboratory-laser-communications-terminal-launches-artemis-ii-0402",
      "time": 1775134800.0,
      "published_at_eastern": "2026-04-02T09:00:00-04:00"
    },
    {
      "title": "MIT researchers measure traffic emissions, to the block, in real-time",
      "url": "https://news.mit.edu/2026/mit-researchers-measure-traffic-emissions-block-real-time-0402",
      "time": 1775120400.0,
      "published_at_eastern": "2026-04-02T05:00:00-04:00"
    },
    {
      "title": "Evaluating the ethics of autonomous systems",
      "url": "https://news.mit.edu/2026/evaluating-autonomous-systems-ethics-0402",
      "time": 1775102400.0,
      "published_at_eastern": "2026-04-02T00:00:00-04:00"
    },
    {
      "title": "Preview tool helps makers visualize 3D-printed objects",
      "url": "https://news.mit.edu/2026/preview-tool-helps-makers-visualize-3d-printed-objects-0401",
      "time": 1775016000.0,
      "published_at_eastern": "2026-04-01T00:00:00-04:00"
    },
    {
      "title": "Two physicists and a curious host walk into a studio…",
      "url": "https://news.mit.edu/2026/two-physicists-and-curious-host-walk-studio",
      "time": 1774998000.0,
      "published_at_eastern": "2026-03-31T19:00:00-04:00"
    },
    {
      "title": "Building the blocks of life",
      "url": "https://news.mit.edu/2026/building-blocks-of-life-sergei-kotelnikov-0331",
      "time": 1774990200.0,
      "published_at_eastern": "2026-03-31T16:50:00-04:00"
    },
    {
      "title": "Tomás Palacios named director of the Institute for Soldier Nanotechnologies",
      "url": "https://news.mit.edu/2026/tomas-palacios-named-director-institute-soldier-nanotechnologies-0331",
      "time": 1774988100.0,
      "published_at_eastern": "2026-03-31T16:15:00-04:00"
    },
    {
      "title": "Turning muscles into motors gives static organs new life",
      "url": "https://news.mit.edu/2026/turning-muscles-into-motors-gives-static-organs-new-life-0331",
      "time": 1774981800.0,
      "published_at_eastern": "2026-03-31T14:30:00-04:00"
    },
    {
      "title": "Climate change may produce “fast-food” phytoplankton",
      "url": "https://news.mit.edu/2026/climate-change-may-produce-fast-food-phytoplankton-0331",
      "time": 1774947600.0,
      "published_at_eastern": "2026-03-31T05:00:00-04:00"
    },
    {
      "title": "MIT researchers use AI to uncover atomic defects in materials ",
      "url": "https://news.mit.edu/2026/mit-researchers-use-ai-uncover-atomic-defects-materials-0330",
      "time": 1774882800.0,
      "published_at_eastern": "2026-03-30T11:00:00-04:00"
    },
    {
      "title": "MIT hackathon tackles real-world challenges in Ukraine",
      "url": "https://news.mit.edu/2026/mit-hackathon-tackles-real-world-challenges-ukraine-0327",
      "time": 1774644000.0,
      "published_at_eastern": "2026-03-27T16:40:00-04:00"
    },
    {
      "title": "Seeing sounds",
      "url": "https://news.mit.edu/2026/seeing-sounds-mariano-salcedo-0326",
      "time": 1774557900.0,
      "published_at_eastern": "2026-03-26T16:45:00-04:00"
    },
    {
      "title": "G. Anthony Grant named a 2025-26 NACDA Athletics Director of the Year",
      "url": "https://news.mit.edu/2026/g-anthony-grant-named-nacda-athletics-director-of-the-year-0326",
      "time": 1774553400.0,
      "published_at_eastern": "2026-03-26T15:30:00-04:00"
    },
    {
      "title": "Implantable islet cells could control diabetes without insulin injections",
      "url": "https://news.mit.edu/2026/implantable-islet-cells-could-control-diabetes-without-insulin-injections-0326",
      "time": 1774537200.0,
      "published_at_eastern": "2026-03-26T11:00:00-04:00"
    },
    {
      "title": "Study reveals why some cancer therapies don’t work for all patients",
      "url": "https://news.mit.edu/2026/study-reveals-why-some-cancer-therapies-dont-work-all-patients-0326",
      "time": 1774537200.0,
      "published_at_eastern": "2026-03-26T11:00:00-04:00"
    }
  ]
}